[{"username":"admin1","password":"$2a$12$6lU7JRPa1lbbxnZlGBGJVOWcLxCxKphY2hyhMFydu8Yiyn.kWLAou","isAdmin":true,"money":null},{"username":"user1","password":"$2a$12$6lU7JRPa1lbbxnZlGBGJVOWcLxCxKphY2hyhMFydu8Yiyn.kWLAou","isAdmin":false,"money":1900},{"username":"user2","password":"$2a$12$6lU7JRPa1lbbxnZlGBGJVOWcLxCxKphY2hyhMFydu8Yiyn.kWLAou","isAdmin":false,"money":500},{"username":"user7","password":"$2b$12$T.n2H13YCP/JsrULUzTAlexMZrKWDaxAPrdYlJM3nTaBSE/c/I5Ai","isAdmin":false,"money":15},{"username":"admin4","password":"$2b$12$ZgKagzXkbw4SFX9ysSYX4unt7dUO.1disk4./ojHIPYy8fgxYQYE.","isAdmin":true},{"username":"admin2","password":"$2b$12$c1gZsb9m7rKd/DFcKhJrfuaA6fl.Gmx5D/0p4TaddFjjnUg6deQYW","isAdmin":true},{"username":"admin3","password":"$2b$12$HOEmx3u0d8BlItdBkl/tGOglP8lNDkMGS9TEFvSKoLRso9AyodmJO","isAdmin":true}]